software_hut_logger/__init__.py
software_hut_logger/accelerate_config.yml
software_hut_logger/cli.py
software_hut_logger/shl_dataset.py
software_hut_logger/shl_logger.py
software_hut_logger/shl_server.py
software_hut_logger/shl_train.py
software_hut_logger/utils.py
software_hut_logger-0.2.2.dist-info/METADATA
software_hut_logger-0.2.2.dist-info/WHEEL
software_hut_logger-0.2.2.dist-info/entry_points.txt
software_hut_logger-0.2.2.dist-info/RECORD
