Metadata-Version: 2.4
Name: software-hut-logger
Version: 0.2.2
Summary: A package containing the logger demo for Software Hut using Hugging Face 🤗 Transformers Trainer.
Author-email: William Thorne <wthorne1@sheffield.ac.uk>
Requires-Python: >=3.10
Requires-Dist: aiofiles>=24.1.0
Requires-Dist: datasets>=3.3.2
Requires-Dist: fastapi>=0.115.8
Requires-Dist: psutil>=7.0.0
Requires-Dist: python-multipart>=0.0.20
Requires-Dist: uvicorn>=0.34.0
Provides-Extra: train
Requires-Dist: accelerate>=1.4.0; extra == 'train'
Requires-Dist: evaluate>=0.4.3; extra == 'train'
Requires-Dist: meteor>=2.0.17; extra == 'train'
Requires-Dist: rouge-score>=0.1.2; extra == 'train'
Requires-Dist: sacrebleu>=2.5.1; extra == 'train'
Requires-Dist: torch>=2.6.0; extra == 'train'
Requires-Dist: transformers>=4.49.0; extra == 'train'
Requires-Dist: wandb>=0.19.7; extra == 'train'
